taskprocessor.py
taskprocessor-0.0.1.dist-info/METADATA
taskprocessor-0.0.1.dist-info/RECORD
taskprocessor-0.0.1.dist-info/WHEEL
taskprocessor-0.0.1.dist-info/top_level.txt
